alchimia/__init__.py
alchimia/engine.py
alchimia/strategy.py
alchimia-0.8.1.dist-info/DESCRIPTION.rst
alchimia-0.8.1.dist-info/METADATA
alchimia-0.8.1.dist-info/RECORD
alchimia-0.8.1.dist-info/WHEEL
alchimia-0.8.1.dist-info/metadata.json
alchimia-0.8.1.dist-info/pbr.json
alchimia-0.8.1.dist-info/top_level.txt
