Metadata-Version: 1.0
Name: alchimia
Version: 0.8.1
Summary: (SQLAlchemy - ORM) + Twisted = win
Home-page: https://github.com/alex/alchimia
Author: Alex Gaynor and David Reid
Author-email: UNKNOWN
License: UNKNOWN
Platform: UNKNOWN
